odoo/addons/l10n_es_aeat_mod303/README.rst
odoo/addons/l10n_es_aeat_mod303/__init__.py
odoo/addons/l10n_es_aeat_mod303/__manifest__.py
odoo/addons/l10n_es_aeat_mod303/data/aeat_export_mod303_2017_data.xml
odoo/addons/l10n_es_aeat_mod303/data/aeat_export_mod303_2018_data.xml
odoo/addons/l10n_es_aeat_mod303/data/aeat_export_mod303_2021_data.xml
odoo/addons/l10n_es_aeat_mod303/data/aeat_export_mod303_data.xml
odoo/addons/l10n_es_aeat_mod303/data/l10n.es.aeat.mod303.report.activity.code.csv
odoo/addons/l10n_es_aeat_mod303/data/tax_code_map_mod303_data.xml
odoo/addons/l10n_es_aeat_mod303/data/2021-07/aeat.model.export.config.csv
odoo/addons/l10n_es_aeat_mod303/data/2021-07/aeat.model.export.config.line.csv
odoo/addons/l10n_es_aeat_mod303/data/2021-07/l10n.es.aeat.map.tax.csv
odoo/addons/l10n_es_aeat_mod303/data/2021-07/l10n.es.aeat.map.tax.line.csv
odoo/addons/l10n_es_aeat_mod303/data/2022/aeat.model.export.config.csv
odoo/addons/l10n_es_aeat_mod303/data/2022/aeat.model.export.config.line.csv
odoo/addons/l10n_es_aeat_mod303/data/2023/aeat.model.export.config.csv
odoo/addons/l10n_es_aeat_mod303/data/2023/aeat.model.export.config.line.csv
odoo/addons/l10n_es_aeat_mod303/data/2023/l10n.es.aeat.map.tax.csv
odoo/addons/l10n_es_aeat_mod303/data/2023/l10n.es.aeat.map.tax.line.csv
odoo/addons/l10n_es_aeat_mod303/data/2024-10/aeat.model.export.config.csv
odoo/addons/l10n_es_aeat_mod303/data/2024-10/aeat.model.export.config.line.csv
odoo/addons/l10n_es_aeat_mod303/data/2024-10/l10n.es.aeat.map.tax.csv
odoo/addons/l10n_es_aeat_mod303/data/2024-10/l10n.es.aeat.map.tax.line.csv
odoo/addons/l10n_es_aeat_mod303/docs/303_register_design_e15v32.xlsx
odoo/addons/l10n_es_aeat_mod303/docs/DR303e15v34.xlsx
odoo/addons/l10n_es_aeat_mod303/docs/DR303e17v20_04.xlsx
odoo/addons/l10n_es_aeat_mod303/docs/DR303e18v10_00.xlsx
odoo/addons/l10n_es_aeat_mod303/docs/DR303e18v10_40.xlsx
odoo/addons/l10n_es_aeat_mod303/docs/DR303e22.xlsx
odoo/addons/l10n_es_aeat_mod303/docs/DR303e23.xlsx
odoo12_addon_l10n_es_aeat_mod303-12.0.5.1.0.dist-info/METADATA
odoo12_addon_l10n_es_aeat_mod303-12.0.5.1.0.dist-info/WHEEL
odoo12_addon_l10n_es_aeat_mod303-12.0.5.1.0.dist-info/top_level.txt
odoo12_addon_l10n_es_aeat_mod303-12.0.5.1.0.dist-info/RECORD
